probabilityestimation/__init__.py
probabilityestimation/estimation/__init__.py
probabilityestimation/estimation/mle.py
probabilityestimation/estimation/plot.py
probabilityestimation/estimation/summary.py
probabilityestimation/probability/__init__.py
probabilityestimation/probability/exponential.py
probabilityestimation/probability/gamma.py
probabilityestimation/probability/poisson.py
probabilityestimation-0.2.dist-info/LICENSE.txt
probabilityestimation-0.2.dist-info/METADATA
probabilityestimation-0.2.dist-info/WHEEL
probabilityestimation-0.2.dist-info/top_level.txt
probabilityestimation-0.2.dist-info/RECORD
