Metadata-Version: 2.1
Name: probabilityestimation
Version: 0.2
Summary: A python package for computing information about Poisson, Gamma, and Exponential distributions.
Home-page: https://github.com/SaraAnnHall/533Lab4_SaraJustine.git
Author: Sara Hall and Justine Filion
Author-email: saraannh@student.ubc.ca, filionjustine05@gmail.com
License: MIT
Platform: UNKNOWN
Requires-Dist: numpy
Requires-Dist: pandas
Requires-Dist: scipy
Requires-Dist: matplotlib
Requires-Dist: plotly
